Metadata-Version: 2.1
Name: simplepyqlearning
Version: 1.0.1
Summary: A simple python lib to do QLearning
Home-page: https://github.com/AdrienDumontet/SimplePyAI
Author: LeLaboDuGame, https://twitch.tv/LeLaboDuGame
Author-email: 
License: Let the package like is it
Platform: UNKNOWN
